LICENSE
README.md
setup.py
enrichrpy/__init__.py
enrichrpy/enrichr.py
enrichrpy/plotting.py
enrichrpy.egg-info/PKG-INFO
enrichrpy.egg-info/SOURCES.txt
enrichrpy.egg-info/dependency_links.txt
enrichrpy.egg-info/requires.txt
enrichrpy.egg-info/top_level.txt