Metadata-Version: 2.1
Name: enrichrpy
Version: 0.1.0
Summary: A tool for gene set enrichment (GSEA) plots and analysis in Python. Built on top of Enrichr API.
Home-page: https://github.com/estorrs/enrichrpy
Author: Erik Storrs
Author-email: epstorrs@gmail.com
Keywords: GSEA gene set enrichment plot figure analysis enrichr
Classifier: License :: OSI Approved :: MIT License
Requires-Python: >=3.6
License-File: LICENSE
